mypackage/__init__.py
mypackage/main.py
scraperWeb-0.0.1.dist-info/METADATA
scraperWeb-0.0.1.dist-info/WHEEL
scraperWeb-0.0.1.dist-info/top_level.txt
scraperWeb-0.0.1.dist-info/RECORD
