Metadata-Version: 2.1
Name: scraperWeb
Version: 0.0.1
Summary: test package for documentation
Home-page: https://github.com/Ayoublee/webscraping
Author: Ayoublee
Author-email: ayoubleepro@gmail.com
Project-URL: Bug Tracker, https://github.com/Ayoublee/webscraping/issues
Classifier: Programming Language :: Python :: 3
Classifier: License :: OSI Approved :: MIT License
Classifier: Operating System :: OS Independent
Requires-Python: >=3.6
